CHANGES.rst
CONTRIBUTORS.rst
MANIFEST.in
README.rst
bootstrap.py
buildout.cfg
setup.py
travis.cfg
buildout.d/base.cfg
buildout.d/checkouts.cfg
buildout.d/development.cfg
buildout.d/jenkins.cfg
buildout.d/sources.cfg
buildout.d/versions.cfg
docs/LICENSE.GPL
docs/LICENSE.rst
src/collective/__init__.py
src/collective.contact.contactlist.egg-info/PKG-INFO
src/collective.contact.contactlist.egg-info/SOURCES.txt
src/collective.contact.contactlist.egg-info/dependency_links.txt
src/collective.contact.contactlist.egg-info/entry_points.txt
src/collective.contact.contactlist.egg-info/namespace_packages.txt
src/collective.contact.contactlist.egg-info/not-zip-safe
src/collective.contact.contactlist.egg-info/requires.txt
src/collective.contact.contactlist.egg-info/top_level.txt
src/collective/contact/__init__.py
src/collective/contact/contactlist/__init__.py
src/collective/contact/contactlist/adapter.py
src/collective/contact/contactlist/api.py
src/collective/contact/contactlist/configure.zcml
src/collective/contact/contactlist/interfaces.py
src/collective/contact/contactlist/setuphandlers.py
src/collective/contact/contactlist/source.py
src/collective/contact/contactlist/testing.py
src/collective/contact/contactlist/testing.zcml
src/collective/contact/contactlist/vocabularies.py
src/collective/contact/contactlist/browser/__init__.py
src/collective/contact/contactlist/browser/addtolist.py
src/collective/contact/contactlist/browser/configure.zcml
src/collective/contact/contactlist/browser/excelexport.py
src/collective/contact/contactlist/browser/excelexport.zcml
src/collective/contact/contactlist/browser/facetednav.py
src/collective/contact/contactlist/browser/facetednav.zcml
src/collective/contact/contactlist/browser/removefromlist.py
src/collective/contact/contactlist/browser/replacelist.py
src/collective/contact/contactlist/browser/view.py
src/collective/contact/contactlist/browser/eeawidget/__init__.py
src/collective/contact/contactlist/browser/eeawidget/configure.zcml
src/collective/contact/contactlist/browser/eeawidget/widget.py
src/collective/contact/contactlist/browser/static/.gitkeep
src/collective/contact/contactlist/browser/static/javascript.js
src/collective/contact/contactlist/content/__init__.py
src/collective/contact/contactlist/content/configure.zcml
src/collective/contact/contactlist/content/contactlist.py
src/collective/contact/contactlist/locales/collective.contact.contactlist.pot
