Metadata-Version: 2.1
Name: collective.contact.contactlist
Version: 1.3
Summary: Manage lists of contacts
Home-page: http://pypi.python.org/pypi/collective.contact.contactlist
Author: Thomas Desvenain
Author-email: thomas.desvenain@gmail.com
License: GPL
Keywords: crm
Platform: UNKNOWN
Classifier: Environment :: Web Environment
Classifier: Framework :: Plone
Classifier: Framework :: Plone :: 4.3
Classifier: Programming Language :: Python
Classifier: Programming Language :: Python :: 2.7
Provides-Extra: test
